pacifica_metadata-0.13.0-py3.8-nspkg.pth
pacifica/metadata/__init__.py
pacifica/metadata/__main__.py
pacifica/metadata/admin_cmd.py
pacifica/metadata/client.py
pacifica/metadata/config.py
pacifica/metadata/globals.py
pacifica/metadata/wsgi.py
pacifica/metadata/orm/__init__.py
pacifica/metadata/orm/all_objects.py
pacifica/metadata/orm/analytical_tools.py
pacifica/metadata/orm/atool_project.py
pacifica/metadata/orm/atool_transaction.py
pacifica/metadata/orm/base.py
pacifica/metadata/orm/citation_contributor.py
pacifica/metadata/orm/citation_doi.py
pacifica/metadata/orm/citation_keyword.py
pacifica/metadata/orm/citation_project.py
pacifica/metadata/orm/citation_transaction.py
pacifica/metadata/orm/citations.py
pacifica/metadata/orm/contributors.py
pacifica/metadata/orm/data_sources.py
pacifica/metadata/orm/dataset_file.py
pacifica/metadata/orm/dataset_project_user.py
pacifica/metadata/orm/datasets.py
pacifica/metadata/orm/doi_author_mapping.py
pacifica/metadata/orm/doi_authors.py
pacifica/metadata/orm/doi_entries.py
pacifica/metadata/orm/doi_info.py
pacifica/metadata/orm/doi_transaction.py
pacifica/metadata/orm/file_key_value.py
pacifica/metadata/orm/files.py
pacifica/metadata/orm/globals.py
pacifica/metadata/orm/groups.py
pacifica/metadata/orm/institution_user.py
pacifica/metadata/orm/institutions.py
pacifica/metadata/orm/instrument_data_source.py
pacifica/metadata/orm/instrument_group.py
pacifica/metadata/orm/instrument_key_value.py
pacifica/metadata/orm/instrument_user.py
pacifica/metadata/orm/instruments.py
pacifica/metadata/orm/journals.py
pacifica/metadata/orm/keys.py
pacifica/metadata/orm/keywords.py
pacifica/metadata/orm/project_group.py
pacifica/metadata/orm/project_instrument.py
pacifica/metadata/orm/project_user.py
pacifica/metadata/orm/projects.py
pacifica/metadata/orm/relationships.py
pacifica/metadata/orm/sync.py
pacifica/metadata/orm/trans_key_value.py
pacifica/metadata/orm/transaction_user.py
pacifica/metadata/orm/transactions.py
pacifica_metadata-0.13.0.dist-info/LICENSE
pacifica_metadata-0.13.0.dist-info/METADATA
pacifica_metadata-0.13.0.dist-info/WHEEL
pacifica_metadata-0.13.0.dist-info/entry_points.txt
pacifica_metadata-0.13.0.dist-info/namespace_packages.txt
pacifica_metadata-0.13.0.dist-info/top_level.txt
pacifica_metadata-0.13.0.dist-info/RECORD
