Metadata-Version: 2.1
Name: pacifica-metadata
Version: 0.13.0
Summary: Pacifica Metadata
Home-page: https://github.com/pacifica/pacifica-metadata/
Author: David Brown
Author-email: dmlb2000@gmail.com
License: UNKNOWN
Platform: UNKNOWN
Requires-Dist: cherrypy
Requires-Dist: peewee (>2)
Requires-Dist: psycopg2
Requires-Dist: python-dateutil
Requires-Dist: requests
